<annotation>
	<folder>jeans</folder>
	<filename>Jeans_000047.jpg</filename>
	<path>C:\Projects\Object Detection Reference\P6_1\models\research\object_detection\images\jeans\Jeans_000047.jpg</path>
	<source>
		<database>Unknown</database>
	</source>
	<size>
		<width>428</width>
		<height>500</height>
		<depth>3</depth>
	</size>
	<segmented>0</segmented>
	<object>
		<name>Jeans</name>
		<pose>Unspecified</pose>
		<truncated>1</truncated>
		<difficult>0</difficult>
		<bndbox>
			<xmin>84</xmin>
			<ymin>1</ymin>
			<xmax>286</xmax>
			<ymax>439</ymax>
		</bndbox>
	</object>
</annotation>
